odoo/addons/account_invoice_report_hide_line/README.rst
odoo/addons/account_invoice_report_hide_line/__init__.py
odoo/addons/account_invoice_report_hide_line/__manifest__.py
odoo/addons/account_invoice_report_hide_line/i18n/account_invoice_report_hide_line.pot
odoo/addons/account_invoice_report_hide_line/i18n/de.po
odoo/addons/account_invoice_report_hide_line/i18n/es.po
odoo/addons/account_invoice_report_hide_line/i18n/hr.po
odoo/addons/account_invoice_report_hide_line/i18n/it.po
odoo/addons/account_invoice_report_hide_line/models/__init__.py
odoo/addons/account_invoice_report_hide_line/models/account_invoice.py
odoo/addons/account_invoice_report_hide_line/readme/CONTRIBUTORS.rst
odoo/addons/account_invoice_report_hide_line/readme/CREDITS.rst
odoo/addons/account_invoice_report_hide_line/readme/DESCRIPTION.rst
odoo/addons/account_invoice_report_hide_line/readme/USAGE.rst
odoo/addons/account_invoice_report_hide_line/static/description/icon.png
odoo/addons/account_invoice_report_hide_line/static/description/index.html
odoo/addons/account_invoice_report_hide_line/tests/__init__.py
odoo/addons/account_invoice_report_hide_line/tests/test_account_invoice_report.py
odoo/addons/account_invoice_report_hide_line/views/account_move_view.xml
odoo/addons/account_invoice_report_hide_line/views/report_invoice.xml
odoo14_addon_account_invoice_report_hide_line-14.0.1.0.1.dev10.dist-info/METADATA
odoo14_addon_account_invoice_report_hide_line-14.0.1.0.1.dev10.dist-info/WHEEL
odoo14_addon_account_invoice_report_hide_line-14.0.1.0.1.dev10.dist-info/top_level.txt
odoo14_addon_account_invoice_report_hide_line-14.0.1.0.1.dev10.dist-info/RECORD
